ucdp_common-0.3.0.dist-info/METADATA
ucdp_common-0.3.0.dist-info/WHEEL
ucdp_common-0.3.0.dist-info/entry_points.txt
ucdp_common-0.3.0.dist-info/licenses/LICENSE
ucdp_common/__init__.py
ucdp_common/fileliststandard.py
ucdp_common/ucdp_afifo.py
ucdp_common/ucdp_afifo/rtl/ucdp_afifo.sv
ucdp_common/ucdp_clk_buf.py
ucdp_common/ucdp_clk_buf/rtl/ucdp_clk_buf.sv
ucdp_common/ucdp_clk_gate.py
ucdp_common/ucdp_clk_gate/rtl/ucdp_clk_gate.sv
ucdp_common/ucdp_clk_mux.py
ucdp_common/ucdp_clk_mux/rtl/ucdp_clk_mux.sv
ucdp_common/ucdp_clk_or.py
ucdp_common/ucdp_clk_or/rtl/ucdp_clk_or.sv
ucdp_common/ucdp_latch.py
ucdp_common/ucdp_latch/rtl/ucdp_latch.sv
ucdp_common/ucdp_sfifo.py
ucdp_common/ucdp_sfifo/rtl/ucdp_sfifo.sv
ucdp_common/ucdp_sync.py
ucdp_common/ucdp_sync/rtl/ucdp_sync.sv
ucdp_common/ucdp_sync_leaf_one.py
ucdp_common/ucdp_sync_leaf_one/rtl/ucdp_sync_leaf_one.sv
ucdp_common/ucdp_sync_leaf_zero.py
ucdp_common/ucdp_sync_leaf_zero/rtl/ucdp_sync_leaf_zero.sv
ucdp_common-0.3.0.dist-info/RECORD
