Metadata-Version: 2.1
Name: ucdp-common
Version: 0.3.0
Summary: Unified Chip Design Platform - Common Modules
Classifier: Programming Language :: Python :: 3
Classifier: Operating System :: OS Independent
Project-URL: Homepage, https://github.com/nbiotcloud/ucdp-common
Project-URL: Documentation, https://ucdp-common.readthedocs.io/en/stable/
Project-URL: Bug Tracker, https://github.com/nbiotcloud/ucdp-common/issues
Requires-Python: <4.0,>=3.10.0
Requires-Dist: ucdp-glbl>=1.4.0
